<?xml version="1.0" encoding="UTF-8"?>
<binding xmlns="http://www.castor.org/SourceGenerator/Binding" defaultBindingType="type"><package><name>com.ffcs.crmd.cas.bean.casbean.presaleorder</name><schemaLocation>presaleorder/preSaleOrder.xsd</schemaLocation></package><package><name>com.ffcs.crmd.cas.bean.casbean.presaleorder</name><schemaLocation>presaleorder/preSaleOrderAttr.xsd</schemaLocation></package><package><name>com.ffcs.crmd.cas.bean.casbean.presaleorder</name><schemaLocation>presaleorder/preSaleOrderPool.xsd</schemaLocation></package><package><name>com.ffcs.crmd.cas.bean.casbean.presaleorder</name><schemaLocation>presaleorder/iSaleAcctItem.xsd</schemaLocation></package><package><name>com.ffcs.crmd.cas.bean.casbean.presaleorder</name><schemaLocation>presaleorder/preSaleAcctItem.xsd</schemaLocation></package><package><name>com.ffcs.crmd.cas.bean.casbean.presaleorder</name><schemaLocation>presaleorder/preSaleAcctItemAttr.xsd</schemaLocation></package><package><name>com.ffcs.crmd.cas.bean.casbean.presaleorder</name><schemaLocation>presaleorder/preSaleOrderItem.xsd</schemaLocation></package><package><name>com.ffcs.crmd.cas.bean.casbean.comm</name><schemaLocation>comm.xsd</schemaLocation></package><package><name>com.ffcs.crmd.cas.bean.casbean.cancel.cancelorderquery</name><schemaLocation>cancel/cancelOrderQuery.xsd</schemaLocation></package><package><name>com.ffcs.crmd.cas.bean.casbean.cancel.cancelordercommit</name><schemaLocation>cancel/cancelOrderCommit.xsd</schemaLocation></package><package><name>com.ffcs.crmd.cas.bean.casbean.query.querypreorderstatus</name><schemaLocation>query/queryPreOrderStatus.xsd</schemaLocation></package><package><name>com.ffcs.crmd.cas.bean.casbean.query.querypreorderisrelation</name><schemaLocation>query/queryPreOrderIsRelation.xsd</schemaLocation></package><package><name>com.ffcs.crmd.cas.bean.casbean.autogenordersave</name><schemaLocation>autogenorder/autoGenOrderSave.xsd</schemaLocation></package><package><name>com.ffcs.crmd.cas.bean.casbean.autogenorder</name><schemaLocation>autogenorder/autoGenOrder.xsd</schemaLocation></package><package><name>com.ffcs.crmd.cas.bean.casbean.autogenordercomplete</name><schemaLocation>autogenorder/autoGenOrderComplete.xsd</schemaLocation></package><package><name>com.ffcs.crmd.cas.bean.casbean.droppresaleordertocrm</name><schemaLocation>presaleorderdeal/dropPreSaleOrderToCrm.xsd</schemaLocation></package><package><name>com.ffcs.crmd.cas.bean.casbean.modpresaleorder</name><schemaLocation>presaleorderdeal/modPreSaleOrder.xsd</schemaLocation></package><package><name>com.ffcs.crmd.cas.bean.casbean.query.presaleorderhasfee</name><schemaLocation>query/preSaleOrderHasFee.xsd</schemaLocation></package><package><name>com.ffcs.crmd.cas.bean.casbean.query.querypreOrder</name><schemaLocation>query/queryPreOrder.xsd</schemaLocation></package><package><name>com.ffcs.crmd.cas.bean.casbean.presaleorderdeal</name><schemaLocation>save/preSaleOrderDeal.xsd</schemaLocation></package><package><name>com.ffcs.crmd.cas.bean.casbean.preordercommitcheck</name><schemaLocation>preordercommitcheck/preOrderCommitCheck.xsd</schemaLocation></package><package><name>com.ffcs.crmd.cas.bean.casbean.presaleordercommit</name><schemaLocation>save/preSaleOrderCommit.xsd</schemaLocation></package><package><name>com.ffcs.crmd.cas.bean.casbean.presaleorderpoolcommit</name><schemaLocation>save/preSaleOrderPoolCommit.xsd</schemaLocation></package><package><name>com.ffcs.crmd.cas.bean.casbean.intfpreordercommit</name><schemaLocation>save/intfPreOrderCommit.xsd</schemaLocation></package><package><name>com.ffcs.crmd.cas.bean.casbean.query.querypreorderflow</name><schemaLocation>query/queryPreOrderFlow.xsd</schemaLocation></package><package><name>com.ffcs.crmd.cas.bean.casbean.query.querypreorderinfo</name><schemaLocation>query/queryPreOrderInfo.xsd</schemaLocation></package><package><name>com.ffcs.crmd.cas.bean.casbean.query.querypreorderfororder</name><schemaLocation>query/queryPreOrderForOrder.xsd</schemaLocation></package><package><name>com.ffcs.crmd.cas.bean.casbean.query.queryPreSaleOrder</name><schemaLocation>query/queryPreSaleOrder.xsd</schemaLocation></package><package><name>com.ffcs.crmd.cas.bean.casbean.query.preSaleOrderCount</name><schemaLocation>query/preSaleOrderCount.xsd</schemaLocation></package><package><name>com.ffcs.crmd.cas.bean.casbean.query.queryReturnList</name><schemaLocation>query/queryReturnList.xsd</schemaLocation></package><package><name>com.ffcs.crmd.cas.bean.casbean.save.returntopresale</name><schemaLocation>save/returnToPreSale.xsd</schemaLocation></package><package><name>com.ffcs.crmd.cas.bean.casbean.query.qureryintassignorg</name><schemaLocation>intassignorg/qureryintAssignOrg.xsd</schemaLocation></package><package><name>com.ffcs.crmd.cas.bean.casbean.checkcouldcancel</name><schemaLocation>presaleorderdeal/checkCouldCancel.xsd</schemaLocation></package><package><name>com.ffcs.crmd.cas.bean.casbean.cancelpreorder</name><schemaLocation>cancel/cancelPreOrder.xsd</schemaLocation></package></binding>